{
    "directory_name": "train_2023_08_21_13_10_09",
    "config": {
        "dataset": "dominick_dataset",
        "model": "gpforecaster",
        "output_dir": "mnt_data/results_dnns",
        "ds_seed": 42,
        "epochs": 100,
        "datadir": "mnt_data/data",
        "cpu_monitor_interval": 0.5,
        "seed": 42,
        "timestamp": "2023_08_21_13_10_09"
    },
    "execution_platform": {
        "System": "Linux",
        "Node Name": "lamarrws03",
        "Release": "5.19.0-35-generic",
        "Version": "#36~22.04.1-Ubuntu SMP PREEMPT_DYNAMIC Fri Feb 17 15:17:25 UTC 2",
        "Machine": "x86_64",
        "Processor": "Intel(R) Core(TM) i7-6700 CPU @ 3.40GHz",
        "Physical cores": 4,
        "Total cores": 8,
        "Max Frequency": 4000.0,
        "Min Frequency": 800.0,
        "Current Frequency": 1760.905375,
        "Total": 33542766592,
        "Available": 32220291072,
        "Used": 849911808
    },
    "requirements": [
        "# 3.7.7 (default, Mar 23 2020, 22:36:06)",
        "# [GCC 7.3.0]",
        "wrapt==1.11.2",
        "typed-ast==1.4.0",
        "six==1.12.0",
        "setuptools==41.6.0",
        "pytz==2019.3",
        "python-dateutil==2.8.0",
        "pyparsing==2.4.2",
        "pylint==2.4.3",
        "mccabe==0.6.1",
        "matplotlib==3.1.1",
        "lazy-object-proxy==1.4.3",
        "kiwisolver==1.1.0",
        "isort==4.3.21",
        "cycler==0.10.0",
        "astroid==2.3.2",
        "zipp==3.14.0",
        "zict==2.2.0",
        "xgboost==1.6.2",
        "wheel==0.37.1",
        "werkzeug==2.2.3",
        "urllib3==1.26.14",
        "typing-extensions==4.4.0",
        "tqdm==4.64.1",
        "tornado==6.2",
        "toolz==0.12.0",
        "threadpoolctl==3.1.0",
        "tenacity==8.2.2",
        "tblib==1.7.0",
        "sortedcontainers==2.4.0",
        "smac==1.2",
        "scipy==1.7.3",
        "scikit-learn==0.24.2",
        "rpy2==2.9.4",
        "requests==2.28.2",
        "reportlab==3.6.12",
        "qrcode==7.4.2",
        "pyyaml==6.0",
        "pyrfr==0.8.3",
        "pypng==0.20220715.0",
        "pynvml==11.4.1",
        "pynisher==0.6.4",
        "pymupdf==1.21.1",
        "pydantic==1.10.4",
        "pyarrow==8.0.0",
        "py-rapl==0.1",
        "py-cpuinfo==9.0.0",
        "psutil==5.9.4",
        "plotly==5.13.1",
        "pip==22.3.1",
        "pint==0.18",
        "pillow==9.4.0",
        "partd==1.4.0",
        "pandas==1.3.5",
        "packaging==23.0",
        "orjson==3.8.5",
        "numpy==1.21.6",
        "mxnet==1.9.1",
        "msgpack==1.0.5",
        "markupsafe==2.1.1",
        "locket==1.0.0",
        "liac-arff==2.5.0",
        "joblib==1.2.0",
        "jinja2==3.1.2",
        "itsdangerous==2.1.2",
        "importlib-metadata==6.0.0",
        "idna==3.4",
        "heapdict==1.0.1",
        "graphviz==0.8.4",
        "gluonts==0.11.8",
        "fuzzywuzzy==0.18.0",
        "fsspec==2023.1.0",
        "flask==2.2.3",
        "emcee==3.1.4",
        "distro==1.8.0",
        "distributed==2022.2.0",
        "dask==2022.2.0",
        "dash==2.8.1",
        "dash-table==5.0.0",
        "dash-html-components==2.0.0",
        "dash-core-components==2.0.0",
        "dash-bootstrap-components==1.4.0",
        "cython==0.29.35",
        "configspace==0.4.21",
        "codecarbon==2.1.4",
        "cloudpickle==2.2.1",
        "click==8.1.3",
        "charset-normalizer==3.0.1",
        "certifi==2022.12.7",
        "auto-sklearn==0.15.0",
        "arrow==1.2.3"
    ],
    "results": {
        "history": {
            "loss": [
                402.6427617829901,
                233.9052516319749,
                312.1841875429801,
                159.61413836341998,
                242.21236480103667,
                171.3713958335842,
                162.23070371186418,
                106.69917482000848,
                143.43680741876173,
                112.60807714524755,
                103.79125692794995,
                93.78723414179888,
                79.53910971481551,
                85.10901917839102,
                74.76016890748089,
                78.79333303085912,
                61.59430109797349,
                72.12445812244968,
                61.64078178502232,
                71.78175926989499,
                50.87739862177416,
                63.82309043860561,
                57.68470438981396,
                62.618285804599616,
                51.008778054697046,
                56.87025932096826,
                53.412826722938334,
                59.13059047265175,
                48.874278587433956,
                57.79171990275148,
                47.347957744850135,
                56.01975249923586,
                50.56182838601778,
                52.37078901307905,
                47.143003470182386,
                53.68469531324055,
                49.74942474216222,
                50.52338993437589,
                49.27737121177325,
                48.33556061599503,
                49.659248523214735,
                48.21756602181139,
                50.03782237510803,
                46.04970234186803,
                49.37329134285878,
                46.69116452094013,
                50.713801062491285,
                43.923826475916854,
                48.56827144735215,
                46.74364900063111,
                49.29553429006271,
                44.34789253325623,
                47.048654414053566,
                45.878885088240004,
                48.85451519507024,
                43.97743859569813,
                46.394588172466825,
                45.51873881228191,
                48.03574550742228,
                44.40347586354749,
                47.51087055093876,
                43.590320867225955,
                47.88688482953522,
                45.36038467391626,
                45.86299446346002,
                45.79334162018677,
                45.14980456421887,
                45.71148468625958,
                45.268854261676125,
                46.463961471746615,
                43.89405263921845,
                46.055304536169196,
                44.454281101510205,
                47.473637874225815,
                42.55110520414864
            ]
        },
        "start": 1692616363.4423351,
        "end": 1692620860.5517135,
        "model": null
    },
    "emissions": {
        "timestamp": {
            "0": "2023-08-21T14:27:40"
        },
        "project_name": {
            "0": "codecarbon"
        },
        "run_id": {
            "0": "87e4b515-c611-443e-976e-f72df29baebf"
        },
        "duration": {
            "0": 4497.110845327377
        },
        "emissions": {
            "0": 0.0083818059761698
        },
        "emissions_rate": {
            "0": 0.0018638201868825
        },
        "cpu_power": {
            "0": 4.3475869442920665
        },
        "gpu_power": {
            "0": 0.0
        },
        "ram_power": {
            "0": 11.714675903320314
        },
        "cpu_energy": {
            "0": 0.0135140091639764
        },
        "gpu_energy": {
            "0": 0
        },
        "ram_energy": {
            "0": 0.0143325223183155
        },
        "energy_consumed": {
            "0": 0.0278465314822917
        },
        "country_name": {
            "0": "Germany"
        },
        "country_iso_code": {
            "0": "DEU"
        },
        "region": {
            "0": NaN
        },
        "cloud_provider": {
            "0": NaN
        },
        "cloud_region": {
            "0": NaN
        },
        "os": {
            "0": "Linux-5.19.0-35-generic-x86_64-with-debian-bookworm-sid"
        },
        "python_version": {
            "0": "3.7.7"
        },
        "cpu_count": {
            "0": 8
        },
        "cpu_model": {
            "0": "Intel(R) Core(TM) i7-6700 CPU @ 3.40GHz"
        },
        "gpu_count": {
            "0": NaN
        },
        "gpu_model": {
            "0": NaN
        },
        "longitude": {
            "0": NaN
        },
        "latitude": {
            "0": NaN
        },
        "ram_total_size": {
            "0": 31.2391357421875
        },
        "tracking_mode": {
            "0": "machine"
        },
        "on_cloud": {
            "0": "N"
        }
    },
    "full_log": "results/merged_dnns/train_2023_08_21_13_10_09.tar.gz"
}