{
    "directory_name": "train_2023_09_09_23_57_57",
    "results": {
        "history": {
            "loss": null
        },
        "start": 1694296738.6232293,
        "end": 1694307926.726356,
        "model": null
    },
    "emissions": {
        "timestamp": {
            "0": "2023-09-10T03:05:26"
        },
        "project_name": {
            "0": "codecarbon"
        },
        "run_id": {
            "0": "1ff32068-3387-4f7c-ad73-752810456945"
        },
        "duration": {
            "0": 11188.107615232468
        },
        "emissions": {
            "0": 0.024780950315236
        },
        "emissions_rate": {
            "0": 2.2149367138279144e-06
        },
        "cpu_power": {
            "0": 6.121276069923866
        },
        "gpu_power": {
            "0": 0.0
        },
        "ram_power": {
            "0": 11.708820819854736
        },
        "cpu_energy": {
            "0": 0.0339038995947647
        },
        "gpu_energy": {
            "0": 0
        },
        "ram_energy": {
            "0": 0.0360361549756805
        },
        "energy_consumed": {
            "0": 0.0699400545704441
        },
        "country_name": {
            "0": "Germany"
        },
        "country_iso_code": {
            "0": "DEU"
        },
        "region": {
            "0": NaN
        },
        "cloud_provider": {
            "0": NaN
        },
        "cloud_region": {
            "0": NaN
        },
        "os": {
            "0": "Linux-6.2.0-26-generic-x86_64-with-debian-bookworm-sid"
        },
        "python_version": {
            "0": "3.7.12"
        },
        "codecarbon_version": {
            "0": "2.2.3"
        },
        "cpu_count": {
            "0": 8
        },
        "cpu_model": {
            "0": "Intel(R) Core(TM) i7-6700 CPU @ 3.40GHz"
        },
        "gpu_count": {
            "0": NaN
        },
        "gpu_model": {
            "0": NaN
        },
        "longitude": {
            "0": NaN
        },
        "latitude": {
            "0": NaN
        },
        "ram_total_size": {
            "0": 31.223522186279297
        },
        "tracking_mode": {
            "0": "machine"
        },
        "on_cloud": {
            "0": "N"
        },
        "pue": {
            "0": 1.0
        }
    },
    "config": {
        "dataset": "australian_electricity_demand_dataset",
        "model": "autokeras",
        "output_dir": "mnt_data/autokeras_new/",
        "ds_seed": -1,
        "epochs": 100,
        "datadir": "mnt_data/data",
        "cpu_monitor_interval": 0.5,
        "seed": 42,
        "timestamp": "2023_09_09_23_57_57"
    },
    "requirements": [
        "# 3.7.12 | packaged by conda-forge | (default, Oct 26 2021, 06:08:21)",
        "# [GCC 9.4.0]",
        "wrapt==1.11.2",
        "typed-ast==1.4.0",
        "six==1.12.0",
        "setuptools==41.6.0",
        "pytz==2019.3",
        "python-dateutil==2.8.0",
        "pyparsing==2.4.2",
        "pylint==2.4.3",
        "mccabe==0.6.1",
        "matplotlib==3.1.1",
        "lazy-object-proxy==1.4.3",
        "kiwisolver==1.1.0",
        "isort==4.3.21",
        "cycler==0.10.0",
        "astroid==2.3.2",
        "zipp==3.15.0",
        "wheel==0.40.0",
        "werkzeug==2.2.3",
        "urllib3==1.26.16",
        "typing-extensions==4.6.3",
        "tqdm==4.65.0",
        "toolz==0.12.0",
        "termcolor==2.3.0",
        "tensorflow==2.11.0",
        "tensorflow-io-gcs-filesystem==0.32.0",
        "tensorflow-estimator==2.11.0",
        "tensorboard==2.11.2",
        "tensorboard-plugin-wit==1.8.1",
        "tensorboard-data-server==0.6.1",
        "rsa==4.9",
        "requests==2.31.0",
        "requests-oauthlib==1.3.1",
        "pynvml==11.5.0",
        "pydantic==1.10.9",
        "pyasn1==0.5.0",
        "pyasn1-modules==0.3.0",
        "py-cpuinfo==9.0.0",
        "psutil==5.9.5",
        "protobuf==3.19.6",
        "pip==23.1.2",
        "pandas==1.3.5",
        "packaging==23.1",
        "opt-einsum==3.3.0",
        "oauthlib==3.2.2",
        "numpy==1.21.6",
        "markupsafe==2.1.3",
        "markdown==3.4.3",
        "libclang==16.0.0",
        "kt-legacy==1.0.5",
        "keras==2.11.0",
        "keras-tuner==1.3.5",
        "importlib-metadata==6.6.0",
        "idna==3.4",
        "h5py==3.8.0",
        "grpcio==1.54.2",
        "google-pasta==0.2.0",
        "google-auth==2.20.0",
        "google-auth-oauthlib==0.4.6",
        "gluonts==0.13.2",
        "gast==0.4.0",
        "fuzzywuzzy==0.18.0",
        "flatbuffers==23.5.26",
        "codecarbon==2.2.3",
        "click==8.1.3",
        "charset-normalizer==3.1.0",
        "certifi==2023.5.7",
        "cachetools==5.3.1",
        "autokeras==1.0.20",
        "astunparse==1.6.3",
        "arrow==1.2.3",
        "absl-py==1.4.0"
    ],
    "execution_platform": {
        "System": "Linux",
        "Node Name": "lamarrws03",
        "Release": "6.2.0-26-generic",
        "Version": "#26~22.04.1-Ubuntu SMP PREEMPT_DYNAMIC Thu Jul 13 16:27:29 UTC 2",
        "Machine": "x86_64",
        "Processor": "Intel(R) Core(TM) i7-6700 CPU @ 3.40GHz",
        "Physical cores": 4,
        "Total cores": 8,
        "Max Frequency": 4000.0,
        "Min Frequency": 800.0,
        "Current Frequency": 1700.087125,
        "Total": 33526001664,
        "Available": 31636856832,
        "Used": 1293873152
    },
    "full_log": "results/merged_autokeras_new/train_2023_09_09_23_57_57.tar.gz"
}