{
    "directory_name": "train_2023_03_18_01_29_09",
    "results": {
        "history": {
            "loss": [
                6.487663860321045,
                5.921617813110352,
                5.725487813949585,
                5.427123928070069,
                5.409216833114624,
                5.443697166442871,
                5.218576707839966,
                5.233568563461303,
                5.20647891998291,
                5.072958726882934,
                5.155520448684692,
                5.058346929550171,
                5.053652067184448,
                5.043517189025879,
                5.058764352798462,
                4.964273834228516,
                4.939444389343262,
                4.879065084457397,
                4.875454750061035,
                4.845320253372193,
                4.855264272689819,
                4.824700593948364,
                4.766650953292847,
                4.739791774749756,
                4.71258017539978,
                4.681844730377197,
                4.701109714508057,
                4.694616975784302,
                4.684567337036133,
                4.6608137607574465,
                4.647084560394287,
                4.602793469429016,
                4.594251832962036,
                4.615502724647522,
                4.5848542499542235,
                4.580276193618775,
                4.601775627136231,
                4.622292938232422,
                4.6223397016525265,
                4.648691091537476,
                4.596516380310058,
                4.573558712005616,
                4.707425241470337,
                4.525013408660889,
                4.575947799682617,
                4.550934624671936,
                4.602423553466797,
                4.54079951763153
            ]
        },
        "start": 1679099351.438665,
        "end": 1679099549.2766414,
        "model": null
    },
    "emissions": {
        "timestamp": {
            "0": "2023-03-18T01:32:29"
        },
        "project_name": {
            "0": "codecarbon"
        },
        "run_id": {
            "0": "5eb58779-9400-4801-9022-4e3d3017fc9a"
        },
        "duration": {
            "0": 197.8444027900696
        },
        "emissions": {
            "0": 0.0017121445180028
        },
        "emissions_rate": {
            "0": 0.0086539952298754
        },
        "cpu_power": {
            "0": 31.59170341945668
        },
        "gpu_power": {
            "0": 1.41
        },
        "ram_power": {
            "0": 23.43553590774536
        },
        "cpu_energy": {
            "0": 0.004410512782574
        },
        "gpu_energy": {
            "0": 6.455400863104392e-05
        },
        "ram_energy": {
            "0": 0.001213120976246
        },
        "energy_consumed": {
            "0": 0.0056881877674511
        },
        "country_name": {
            "0": "Germany"
        },
        "country_iso_code": {
            "0": "DEU"
        },
        "region": {
            "0": NaN
        },
        "cloud_provider": {
            "0": NaN
        },
        "cloud_region": {
            "0": NaN
        },
        "os": {
            "0": "Linux-5.4.0-137-generic-x86_64-with-debian-bullseye-sid"
        },
        "python_version": {
            "0": "3.7.7"
        },
        "cpu_count": {
            "0": 20
        },
        "cpu_model": {
            "0": "Intel(R) Xeon(R) W-2155 CPU @ 3.30GHz"
        },
        "gpu_count": {
            "0": 1
        },
        "gpu_model": {
            "0": "1 x Quadro RTX 5000"
        },
        "longitude": {
            "0": NaN
        },
        "latitude": {
            "0": NaN
        },
        "ram_total_size": {
            "0": 62.4947624206543
        },
        "tracking_mode": {
            "0": "machine"
        },
        "on_cloud": {
            "0": "N"
        }
    },
    "execution_platform": {
        "System": "Linux",
        "Node Name": "ls8ws022",
        "Release": "5.4.0-137-generic",
        "Version": "#154-Ubuntu SMP Thu Jan 5 17:03:22 UTC 2023",
        "Machine": "x86_64",
        "Processor": "Intel(R) Xeon(R) W-2155 CPU @ 3.30GHz",
        "Physical cores": 10,
        "Total cores": 20,
        "Max Frequency": 4500.0,
        "Min Frequency": 1200.0,
        "Current Frequency": 1200.5674,
        "Total": 67103240192,
        "Available": 64874766336,
        "Used": 1486274560
    },
    "requirements": [
        "# 3.7.7 (default, Mar 23 2020, 22:36:06)",
        "# [GCC 7.3.0]",
        "wrapt==1.11.2",
        "typed-ast==1.4.0",
        "six==1.12.0",
        "setuptools==41.6.0",
        "pytz==2019.3",
        "python-dateutil==2.8.0",
        "pyparsing==2.4.2",
        "pylint==2.4.3",
        "numpy==1.17.3",
        "mccabe==0.6.1",
        "matplotlib==3.1.1",
        "lazy-object-proxy==1.4.3",
        "kiwisolver==1.1.0",
        "isort==4.3.21",
        "cycler==0.10.0",
        "astroid==2.3.2",
        "zipp==3.14.0",
        "xgboost==1.6.2",
        "wheel==0.37.1",
        "werkzeug==2.2.3",
        "urllib3==1.26.14",
        "typing-extensions==4.4.0",
        "tqdm==4.64.1",
        "toolz==0.12.0",
        "threadpoolctl==3.1.0",
        "tenacity==8.2.2",
        "scipy==1.7.3",
        "scikit-learn==1.0.2",
        "rpy2==2.9.4",
        "requests==2.28.2",
        "reportlab==3.6.12",
        "qrcode==7.4.2",
        "pypng==0.20220715.0",
        "pynvml==11.4.1",
        "pymupdf==1.21.1",
        "pydantic==1.10.4",
        "pyarrow==8.0.0",
        "py-rapl==0.1",
        "py-cpuinfo==9.0.0",
        "psutil==5.9.4",
        "plotly==5.13.1",
        "pip==22.3.1",
        "pint==0.18",
        "pillow==9.4.0",
        "pandas==1.3.5",
        "packaging==23.0",
        "orjson==3.8.5",
        "mxnet==1.9.1",
        "markupsafe==2.1.1",
        "joblib==1.2.0",
        "jinja2==3.1.2",
        "itsdangerous==2.1.2",
        "importlib-metadata==6.0.0",
        "idna==3.4",
        "graphviz==0.8.4",
        "gluonts==0.11.8",
        "fuzzywuzzy==0.18.0",
        "flask==2.2.3",
        "dash==2.8.1",
        "dash-table==5.0.0",
        "dash-html-components==2.0.0",
        "dash-core-components==2.0.0",
        "dash-bootstrap-components==1.4.0",
        "codecarbon==2.1.4",
        "click==8.1.3",
        "charset-normalizer==3.0.1",
        "certifi==2022.12.7",
        "arrow==1.2.3"
    ],
    "config": {
        "dataset": "tourism_quarterly_dataset",
        "model": "wavenet",
        "output_dir": "mnt_data/results",
        "ds_seed": 124,
        "epochs": 100,
        "datadir": "mnt_data/data",
        "cpu_monitor_interval": 0.5,
        "seed": 42,
        "timestamp": "2023_03_18_01_29_09"
    },
    "full_log": "results/merged22/train_2023_03_18_01_29_09.tar.gz"
}