{
    "directory_name": "train_2023_03_18_07_35_37",
    "config": {
        "dataset": "electricity_weekly_dataset",
        "model": "mqrnn",
        "output_dir": "mnt_data/results",
        "ds_seed": 468,
        "epochs": 100,
        "datadir": "mnt_data/data",
        "cpu_monitor_interval": 0.5,
        "seed": 42,
        "timestamp": "2023_03_18_07_35_37"
    },
    "execution_platform": {
        "System": "Linux",
        "Node Name": "ls8ws022",
        "Release": "5.4.0-137-generic",
        "Version": "#154-Ubuntu SMP Thu Jan 5 17:03:22 UTC 2023",
        "Machine": "x86_64",
        "Processor": "Intel(R) Xeon(R) W-2155 CPU @ 3.30GHz",
        "Physical cores": 10,
        "Total cores": 20,
        "Max Frequency": 4500.0,
        "Min Frequency": 1200.0,
        "Current Frequency": 1355.95075,
        "Total": 67103240192,
        "Available": 64866238464,
        "Used": 1494798336
    },
    "requirements": [
        "# 3.7.7 (default, Mar 23 2020, 22:36:06)",
        "# [GCC 7.3.0]",
        "wrapt==1.11.2",
        "typed-ast==1.4.0",
        "six==1.12.0",
        "setuptools==41.6.0",
        "pytz==2019.3",
        "python-dateutil==2.8.0",
        "pyparsing==2.4.2",
        "pylint==2.4.3",
        "numpy==1.17.3",
        "mccabe==0.6.1",
        "matplotlib==3.1.1",
        "lazy-object-proxy==1.4.3",
        "kiwisolver==1.1.0",
        "isort==4.3.21",
        "cycler==0.10.0",
        "astroid==2.3.2",
        "zipp==3.14.0",
        "xgboost==1.6.2",
        "wheel==0.37.1",
        "werkzeug==2.2.3",
        "urllib3==1.26.14",
        "typing-extensions==4.4.0",
        "tqdm==4.64.1",
        "toolz==0.12.0",
        "threadpoolctl==3.1.0",
        "tenacity==8.2.2",
        "scipy==1.7.3",
        "scikit-learn==1.0.2",
        "rpy2==2.9.4",
        "requests==2.28.2",
        "reportlab==3.6.12",
        "qrcode==7.4.2",
        "pypng==0.20220715.0",
        "pynvml==11.4.1",
        "pymupdf==1.21.1",
        "pydantic==1.10.4",
        "pyarrow==8.0.0",
        "py-rapl==0.1",
        "py-cpuinfo==9.0.0",
        "psutil==5.9.4",
        "plotly==5.13.1",
        "pip==22.3.1",
        "pint==0.18",
        "pillow==9.4.0",
        "pandas==1.3.5",
        "packaging==23.0",
        "orjson==3.8.5",
        "mxnet==1.9.1",
        "markupsafe==2.1.1",
        "joblib==1.2.0",
        "jinja2==3.1.2",
        "itsdangerous==2.1.2",
        "importlib-metadata==6.0.0",
        "idna==3.4",
        "graphviz==0.8.4",
        "gluonts==0.11.8",
        "fuzzywuzzy==0.18.0",
        "flask==2.2.3",
        "dash==2.8.1",
        "dash-table==5.0.0",
        "dash-html-components==2.0.0",
        "dash-core-components==2.0.0",
        "dash-bootstrap-components==1.4.0",
        "codecarbon==2.1.4",
        "click==8.1.3",
        "charset-normalizer==3.0.1",
        "certifi==2022.12.7",
        "arrow==1.2.3"
    ],
    "results": {
        "history": {
            "loss": [
                42448.45318359375,
                42440.4711328125,
                42421.134453125,
                42389.00708984375,
                42346.005078125,
                42294.0569140625,
                42233.52876953125,
                42163.9633203125,
                42085.12412109375,
                41999.166171875,
                41907.81794921875,
                41805.61150390625,
                41695.384609375,
                41580.88197265625,
                41485.83248046875,
                41362.34255859375,
                41242.61931640625,
                41132.39447265625,
                40994.74763671875,
                40854.066640625,
                40769.9228125,
                40634.0530078125,
                40543.75837890625,
                40407.65111328125,
                40262.361875,
                40115.259765625,
                39985.87568359375,
                39934.4558203125,
                39821.748984375,
                39718.74470703125,
                39619.86375,
                39497.316171875,
                39376.3130859375,
                39291.3218359375,
                39183.78833984375,
                39140.7144140625,
                39099.35126953125,
                39022.7469140625,
                38865.6376953125,
                38783.134765625,
                38773.19451171875,
                38815.2906640625,
                38742.3059375,
                38603.22560546875,
                38469.33703125,
                38398.23171875,
                38315.38697265625,
                38224.1066015625,
                38220.48306640625,
                38287.18341796875,
                38439.57423828125,
                38847.833984375,
                38997.425625,
                39009.84236328125,
                39150.34623046875,
                39276.006015625,
                39126.07158203125,
                39886.25111328125
            ]
        },
        "start": 1679121339.0111556,
        "end": 1679121493.1201046,
        "model": null
    },
    "emissions": {
        "timestamp": {
            "0": "2023-03-18T07:38:13"
        },
        "project_name": {
            "0": "codecarbon"
        },
        "run_id": {
            "0": "cac31f61-1fb5-4d26-9e3e-b136c817abf3"
        },
        "duration": {
            "0": 154.1158308982849
        },
        "emissions": {
            "0": 0.0011182684236367
        },
        "emissions_rate": {
            "0": 0.0072560256601725
        },
        "cpu_power": {
            "0": 17.837420247453544
        },
        "gpu_power": {
            "0": 0.902
        },
        "ram_power": {
            "0": 23.43553590774536
        },
        "cpu_energy": {
            "0": 0.0026883715298621
        },
        "gpu_energy": {
            "0": 5.413582602971128e-05
        },
        "ram_energy": {
            "0": 0.0009726701312734
        },
        "energy_consumed": {
            "0": 0.0037151774871653
        },
        "country_name": {
            "0": "Germany"
        },
        "country_iso_code": {
            "0": "DEU"
        },
        "region": {
            "0": NaN
        },
        "cloud_provider": {
            "0": NaN
        },
        "cloud_region": {
            "0": NaN
        },
        "os": {
            "0": "Linux-5.4.0-137-generic-x86_64-with-debian-bullseye-sid"
        },
        "python_version": {
            "0": "3.7.7"
        },
        "cpu_count": {
            "0": 20
        },
        "cpu_model": {
            "0": "Intel(R) Xeon(R) W-2155 CPU @ 3.30GHz"
        },
        "gpu_count": {
            "0": 1
        },
        "gpu_model": {
            "0": "1 x Quadro RTX 5000"
        },
        "longitude": {
            "0": NaN
        },
        "latitude": {
            "0": NaN
        },
        "ram_total_size": {
            "0": 62.4947624206543
        },
        "tracking_mode": {
            "0": "machine"
        },
        "on_cloud": {
            "0": "N"
        }
    },
    "full_log": "results/merged22/train_2023_03_18_07_35_37.tar.gz"
}