{
    "directory_name": "train_2023_03_11_11_28_31",
    "results": {
        "history": {
            "loss": [
                7.046702795028686,
                7.637041425704956,
                6.666868190765381,
                6.71880331993103,
                6.963414096832276,
                6.401768388748169,
                7.074594926834107,
                6.5975996685028075,
                6.399051923751831,
                7.111171398162842,
                6.438695440292358,
                6.733586349487305,
                6.638633403778076,
                6.365055360794067,
                6.793398551940918,
                6.545616245269775,
                6.122129678726196,
                6.976782541275025,
                6.305360250473022,
                6.679853477478027,
                6.5163780689239506,
                6.316728677749634,
                6.746618795394897,
                6.4483310317993165,
                6.104463653564453,
                6.9820973777771,
                6.2775815486907955,
                6.639265785217285,
                6.473702774047852,
                6.268599605560302,
                6.736407642364502,
                6.42586932182312,
                6.084061117172241,
                6.970481672286987,
                6.208244667053223,
                6.716780099868775,
                6.425542049407959,
                6.2111107444763185,
                6.8305497646331785,
                6.337581405639648,
                6.5443134784698485,
                6.49009861946106
            ]
        },
        "start": 1678530521.2256,
        "end": 1678534313.0388267,
        "model": null
    },
    "config": {
        "dataset": "m4_daily_dataset",
        "model": "deepstate",
        "output_dir": "mnt_data/results",
        "epochs": 100,
        "datadir": "mnt_data/data",
        "cpu_monitor_interval": 0.5,
        "seed": 42,
        "timestamp": "2023_03_11_11_28_31"
    },
    "requirements": [
        "# 3.7.7 (default, Mar 23 2020, 22:36:06)",
        "# [GCC 7.3.0]",
        "wrapt==1.11.2",
        "typed-ast==1.4.0",
        "six==1.12.0",
        "setuptools==41.6.0",
        "pytz==2019.3",
        "python-dateutil==2.8.0",
        "pyparsing==2.4.2",
        "pylint==2.4.3",
        "numpy==1.17.3",
        "mccabe==0.6.1",
        "matplotlib==3.1.1",
        "lazy-object-proxy==1.4.3",
        "kiwisolver==1.1.0",
        "isort==4.3.21",
        "cycler==0.10.0",
        "astroid==2.3.2",
        "zipp==3.14.0",
        "xgboost==1.6.2",
        "wheel==0.37.1",
        "werkzeug==2.2.3",
        "urllib3==1.26.14",
        "typing-extensions==4.4.0",
        "tqdm==4.64.1",
        "toolz==0.12.0",
        "threadpoolctl==3.1.0",
        "tenacity==8.2.2",
        "scipy==1.7.3",
        "scikit-learn==1.0.2",
        "rpy2==2.9.4",
        "requests==2.28.2",
        "reportlab==3.6.12",
        "qrcode==7.4.2",
        "pypng==0.20220715.0",
        "pynvml==11.4.1",
        "pymupdf==1.21.1",
        "pydantic==1.10.4",
        "pyarrow==8.0.0",
        "py-rapl==0.1",
        "py-cpuinfo==9.0.0",
        "psutil==5.9.4",
        "plotly==5.13.1",
        "pip==22.3.1",
        "pint==0.18",
        "pillow==9.4.0",
        "pandas==1.3.5",
        "packaging==23.0",
        "orjson==3.8.5",
        "mxnet==1.9.1",
        "markupsafe==2.1.1",
        "joblib==1.2.0",
        "jinja2==3.1.2",
        "itsdangerous==2.1.2",
        "importlib-metadata==6.0.0",
        "idna==3.4",
        "graphviz==0.8.4",
        "gluonts==0.11.8",
        "fuzzywuzzy==0.18.0",
        "flask==2.2.3",
        "dash==2.8.1",
        "dash-table==5.0.0",
        "dash-html-components==2.0.0",
        "dash-core-components==2.0.0",
        "dash-bootstrap-components==1.4.0",
        "codecarbon==2.1.4",
        "click==8.1.3",
        "charset-normalizer==3.0.1",
        "certifi==2022.12.7",
        "arrow==1.2.3"
    ],
    "emissions": {
        "timestamp": {
            "0": "2023-03-11T12:31:53"
        },
        "project_name": {
            "0": "codecarbon"
        },
        "run_id": {
            "0": "89260ee1-530d-4bfb-b9a5-bc973ae142d4"
        },
        "duration": {
            "0": 3791.820399284363
        },
        "emissions": {
            "0": 0.0297970498326939
        },
        "emissions_rate": {
            "0": 0.0078582439817871
        },
        "cpu_power": {
            "0": 23.08356774317084
        },
        "gpu_power": {
            "0": 1.063
        },
        "ram_power": {
            "0": 23.43553590774536
        },
        "cpu_energy": {
            "0": 0.0741667934975537
        },
        "gpu_energy": {
            "0": 0.0010467133154657
        },
        "ram_energy": {
            "0": 0.0237800142258313
        },
        "energy_consumed": {
            "0": 0.0989935210388502
        },
        "country_name": {
            "0": "Germany"
        },
        "country_iso_code": {
            "0": "DEU"
        },
        "region": {
            "0": NaN
        },
        "cloud_provider": {
            "0": NaN
        },
        "cloud_region": {
            "0": NaN
        },
        "os": {
            "0": "Linux-5.4.0-137-generic-x86_64-with-debian-bullseye-sid"
        },
        "python_version": {
            "0": "3.7.7"
        },
        "cpu_count": {
            "0": 20
        },
        "cpu_model": {
            "0": "Intel(R) Xeon(R) W-2155 CPU @ 3.30GHz"
        },
        "gpu_count": {
            "0": 1
        },
        "gpu_model": {
            "0": "1 x Quadro RTX 5000"
        },
        "longitude": {
            "0": NaN
        },
        "latitude": {
            "0": NaN
        },
        "ram_total_size": {
            "0": 62.4947624206543
        },
        "tracking_mode": {
            "0": "machine"
        },
        "on_cloud": {
            "0": "N"
        }
    },
    "execution_platform": {
        "System": "Linux",
        "Node Name": "ls8ws022",
        "Release": "5.4.0-137-generic",
        "Version": "#154-Ubuntu SMP Thu Jan 5 17:03:22 UTC 2023",
        "Machine": "x86_64",
        "Processor": "Intel(R) Xeon(R) W-2155 CPU @ 3.30GHz",
        "Physical cores": 10,
        "Total cores": 20,
        "Max Frequency": 4500.0,
        "Min Frequency": 1200.0,
        "Current Frequency": 1206.2139,
        "Total": 67103240192,
        "Available": 64885587968,
        "Used": 1475448832
    },
    "full_log": "results/merged/train_2023_03_11_11_28_31.tar.gz"
}