{
    "directory_name": "infer_2023_01_24_20_55_47",
    "validation_results": {
        "metrics": {
            "aggregated": {
                "MSE": 652293381.8810141,
                "abs_error": 20561995.69765091,
                "abs_target_sum": 116705274.77728981,
                "abs_target_mean": 10508.308551889952,
                "seasonal_error": 1743.9892909919095,
                "MASE": 1.154930852398805,
                "MAPE": 0.22570526653016212,
                "sMAPE": 0.15881295609926074,
                "MSIS": 46.19723413318645,
                "QuantileLoss[0.1]": 27172251.801684078,
                "Coverage[0.1]": 0.5564559697460832,
                "QuantileLoss[0.5]": 20561995.71984415,
                "Coverage[0.5]": 0.5564559697460832,
                "QuantileLoss[0.9]": 13951739.638004228,
                "Coverage[0.9]": 0.5564559697460832,
                "RMSE": 25540.034884099397,
                "NRMSE": 2.4304610735384187,
                "ND": 0.1761873723093462,
                "wQuantileLoss[0.1]": 0.23282796646113244,
                "wQuantileLoss[0.5]": 0.17618737249951105,
                "wQuantileLoss[0.9]": 0.1195467785378897,
                "mean_absolute_QuantileLoss": 20561995.71984415,
                "mean_wQuantileLoss": 0.17618737249951102,
                "MAE_Coverage": 0.2854853232486944,
                "OWA": NaN
            }
        },
        "start": 1674590147.8633134,
        "end": 1674590185.8459983,
        "model": null,
        "data": null
    },
    "validation_pynvml": {
        "0": {
            "start_unix": 1674593747.825984,
            "end_unix": 1674593785.84278,
            "start_utc": "2023-01-24 20:55:47",
            "end_utc": "2023-01-24 20:56:25",
            "total_duration": 38.01679611206055,
            "nr_measurements": 760,
            "temperature": {
                "min": 22,
                "max": 22,
                "mean": 22.0,
                "std": 0.0
            },
            "util.gpu": {
                "min": 0,
                "max": 0,
                "mean": 0.0,
                "std": 0.0
            },
            "util.memory": {
                "min": 0,
                "max": 0,
                "mean": 0.0,
                "std": 0.0
            },
            "power_usage": {
                "min": 0.992,
                "max": 2.292,
                "mean": 1.7229486842105264,
                "std": 0.18666832039843814
            },
            "memory.used": {
                "min": 16384000,
                "max": 16384000,
                "mean": 16384000.0,
                "std": 0.0
            },
            "memory.free": {
                "min": 16892231680,
                "max": 16892231680,
                "mean": 16892231680.0,
                "std": 0.0
            },
            "total_power_draw": 65.53650162329097
        },
        "total": {
            "start_unix": 1674593747.825984,
            "end_unix": 1674593785.84278,
            "nr_measurements": 760,
            "total_power_draw": 65.53650162329097,
            "start_utc": "2023-01-24 20:55:47",
            "end_utc": "2023-01-24 20:56:25",
            "total_duration": 38.01679611206055
        }
    },
    "validation_pyrapl": {
        "0": {
            "start_unix": 1674593747.824204,
            "end_unix": 1674593785.893507,
            "start_utc": "2023-01-24 20:55:47",
            "end_utc": "2023-01-24 20:56:25",
            "total_duration": 38.069303035736084,
            "nr_measurements": 761,
            "duration": {
                "min": 0.002098,
                "max": 0.050479,
                "mean": 0.05002811563731931,
                "std": 0.001738778675476442
            },
            "package-0": {
                "min": 11.898951382268827,
                "max": 156.24383572583704,
                "mean": 82.53629036630507,
                "std": 11.172666739374302
            },
            "package-0.dram": {
                "min": 2.880838894184938,
                "max": 7.665568599265293,
                "mean": 7.246931089369593,
                "std": 0.3111471786950106
            },
            "total_power_draw": 3145.5933879999975
        },
        "total": {
            "start_unix": 1674593747.824204,
            "end_unix": 1674593785.893507,
            "nr_measurements": 761,
            "total_power_draw": 3145.5933879999975,
            "start_utc": "2023-01-24 20:55:47",
            "end_utc": "2023-01-24 20:56:25",
            "total_duration": 38.069303035736084
        }
    },
    "execution_platform": {
        "System": "Linux",
        "Node Name": "ls8ws022",
        "Release": "5.4.0-137-generic",
        "Version": "#154-Ubuntu SMP Thu Jan 5 17:03:22 UTC 2023",
        "Machine": "x86_64",
        "Processor": "Intel(R) Xeon(R) W-2155 CPU @ 3.30GHz"
    },
    "requirements": [
        "# 3.7.7 (default, Mar 23 2020, 22:36:06)",
        "# [GCC 7.3.0]",
        "wrapt==1.11.2",
        "typed-ast==1.4.0",
        "six==1.12.0",
        "setuptools==41.6.0",
        "pytz==2019.3",
        "python-dateutil==2.8.0",
        "pyparsing==2.4.2",
        "pylint==2.4.3",
        "numpy==1.17.3",
        "mccabe==0.6.1",
        "matplotlib==3.1.1",
        "lazy-object-proxy==1.4.3",
        "kiwisolver==1.1.0",
        "isort==4.3.21",
        "cycler==0.10.0",
        "astroid==2.3.2",
        "wheel==0.37.1",
        "urllib3==1.26.14",
        "typing-extensions==4.4.0",
        "tqdm==4.64.1",
        "toolz==0.12.0",
        "rpy2==2.9.4",
        "requests==2.28.2",
        "pynvml==11.4.1",
        "pydantic==1.10.4",
        "pyarrow==8.0.0",
        "py-rapl==0.1",
        "pip==22.3.1",
        "pandas==1.3.5",
        "orjson==3.8.5",
        "mxnet==1.9.1",
        "markupsafe==2.1.1",
        "jinja2==3.1.2",
        "idna==3.4",
        "graphviz==0.8.4",
        "gluonts==0.11.8",
        "charset-normalizer==3.0.1",
        "certifi==2022.12.7"
    ],
    "config": {
        "dataset": "m1_monthly_dataset",
        "model": "nbeats",
        "output_dir": "mnt_data/results",
        "epochs": 100,
        "datadir": "mnt_data/data",
        "cpu_monitor_interval": 0.05,
        "gpu_monitor_interval": 0.05,
        "seed": 42,
        "timestamp": "2023_01_24_20_55_47",
        "lag": 15,
        "train_logdir": "mnt_data/results/train_2023_01_24_20_47_15"
    },
    "full_log": "mnt_data/results_merged/infer_2023_01_24_20_55_47.tar.gz"
}