{
    "directory_name": "infer_2023_03_01_21_22_30",
    "validation_psutil": {
        "61255": {
            "start_unix": 1677705750.39715,
            "end_unix": 1677708554.464507,
            "start_utc": "2023-03-01 21:22:30",
            "end_utc": "2023-03-01 22:09:14",
            "total_duration": 2804.0673570632935,
            "nr_measurements": 55892,
            "cpu_num": {
                "min": 0,
                "max": 19,
                "mean": 10.482573534674014,
                "std": 5.46834973522317
            },
            "cpu_percent": {
                "min": 0.0,
                "max": 1127.0,
                "mean": 786.8156247763544,
                "std": 114.28209797470257
            },
            "mem_rss": {
                "min": 858943488,
                "max": 2176958464,
                "mean": 1579062207.2167752,
                "std": 218361294.45973042
            },
            "mem_vms": {
                "min": 6161010688,
                "max": 7536750592,
                "mean": 7008666763.826237,
                "std": 216609891.44395313
            },
            "mem_shared": {
                "min": 135626752,
                "max": 136396800,
                "mean": 136224637.99384528,
                "std": 8126.103356789386
            },
            "mem_text": {
                "min": 2330624,
                "max": 2330624,
                "mean": 2330624.0,
                "std": 0.0
            },
            "mem_lib": {
                "min": 0,
                "max": 0,
                "mean": 0.0,
                "std": 0.0
            },
            "mem_data": {
                "min": 4268011520,
                "max": 5719687168,
                "mean": 5163970081.087812,
                "std": 217675380.4569052
            },
            "mem_uss": {
                "min": 122720256,
                "max": 1780289536,
                "mean": 1119709819.7403564,
                "std": 270479705.55271935
            },
            "mem_pss": {
                "min": 217283584,
                "max": 1879328768,
                "mean": 1232777322.683461,
                "std": 258203908.6298306
            },
            "total_power_draw": -1
        },
        "total": {
            "start_unix": 1677705750.39715,
            "end_unix": 1677708554.464507,
            "nr_measurements": 55892,
            "total_power_draw": -1,
            "start_utc": "2023-03-01 21:22:30",
            "end_utc": "2023-03-01 22:09:14",
            "total_duration": 2804.0673570632935
        }
    },
    "validation_results": {
        "metrics": {
            "aggregated": {
                "MSE": 171.27990446066372,
                "abs_error": 5160827.565100189,
                "abs_target_sum": 6338863.920570279,
                "abs_target_mean": 6.58815989083965,
                "seasonal_error": 5.035596683611523,
                "MASE": Infinity,
                "MAPE": 96.13118213135635,
                "sMAPE": 1.5821099712027942,
                "MSIS": Infinity,
                "QuantileLoss[0.1]": 1220298.2632578188,
                "Coverage[0.1]": 0.5424409661594746,
                "QuantileLoss[0.5]": 5160827.567924699,
                "Coverage[0.5]": 0.7160254011806768,
                "QuantileLoss[0.9]": 4593289.237896328,
                "Coverage[0.9]": 0.9240739585931654,
                "RMSE": 13.0873948691351,
                "NRMSE": 1.986502314148774,
                "ND": 0.8141565475719966,
                "wQuantileLoss[0.1]": 0.1925105631780204,
                "wQuantileLoss[0.5]": 0.8141565480175827,
                "wQuantileLoss[0.9]": 0.7246234176112571,
                "mean_absolute_QuantileLoss": 3658138.3563596145,
                "mean_wQuantileLoss": 0.5770968429356201,
                "MAE_Coverage": 0.22751344197777226,
                "OWA": NaN
            }
        },
        "start": 1677702150.443877,
        "end": 1677704954.0308075,
        "model": null,
        "data": null
    },
    "requirements": [
        "# 3.7.7 (default, Mar 23 2020, 22:36:06)",
        "# [GCC 7.3.0]",
        "wrapt==1.11.2",
        "typed-ast==1.4.0",
        "six==1.12.0",
        "setuptools==41.6.0",
        "pytz==2019.3",
        "python-dateutil==2.8.0",
        "pyparsing==2.4.2",
        "pylint==2.4.3",
        "numpy==1.17.3",
        "mccabe==0.6.1",
        "matplotlib==3.1.1",
        "lazy-object-proxy==1.4.3",
        "kiwisolver==1.1.0",
        "isort==4.3.21",
        "cycler==0.10.0",
        "astroid==2.3.2",
        "zipp==3.14.0",
        "wheel==0.37.1",
        "urllib3==1.26.14",
        "typing-extensions==4.4.0",
        "tqdm==4.64.1",
        "toolz==0.12.0",
        "rpy2==2.9.4",
        "requests==2.28.2",
        "pynvml==11.4.1",
        "pydantic==1.10.4",
        "pyarrow==8.0.0",
        "py-rapl==0.1",
        "py-cpuinfo==9.0.0",
        "psutil==5.9.4",
        "pip==22.3.1",
        "pandas==1.3.5",
        "orjson==3.8.5",
        "mxnet==1.9.1",
        "markupsafe==2.1.1",
        "jinja2==3.1.2",
        "importlib-metadata==6.0.0",
        "idna==3.4",
        "graphviz==0.8.4",
        "gluonts==0.11.8",
        "fuzzywuzzy==0.18.0",
        "codecarbon==2.1.4",
        "click==8.1.3",
        "charset-normalizer==3.0.1",
        "certifi==2022.12.7",
        "arrow==1.2.3"
    ],
    "validation_pyrapl": {
        "0": {
            "start_unix": 1677705750.390323,
            "end_unix": 1677708554.926614,
            "start_utc": "2023-03-01 21:22:30",
            "end_utc": "2023-03-01 22:09:14",
            "total_duration": 2804.5362911224365,
            "nr_measurements": 55922,
            "duration": {
                "min": 0.002255,
                "max": 0.054854,
                "mean": 0.050150898912771365,
                "std": 0.00023287822417071577
            },
            "package-0": {
                "min": 14.101552106430155,
                "max": 161.93062764513294,
                "mean": 85.19846631667906,
                "std": 10.116338691669938
            },
            "package-0.dram": {
                "min": 3.094013303769401,
                "max": 9.424797800709193,
                "mean": 8.015862165239055,
                "std": 0.38288585344217985
            },
            "total_power_draw": 238941.5271629975
        },
        "total": {
            "start_unix": 1677705750.390323,
            "end_unix": 1677708554.926614,
            "nr_measurements": 55922,
            "total_power_draw": 238941.5271629975,
            "start_utc": "2023-03-01 21:22:30",
            "end_utc": "2023-03-01 22:09:14",
            "total_duration": 2804.5362911224365
        }
    },
    "validation_pynvml": {
        "0": {
            "start_unix": 1677705750.389476,
            "end_unix": 1677708554.02096,
            "start_utc": "2023-03-01 21:22:30",
            "end_utc": "2023-03-01 22:09:14",
            "total_duration": 2803.6314840316772,
            "nr_measurements": 55898,
            "temperature": {
                "min": 26,
                "max": 26,
                "mean": 26.0,
                "std": 0.0
            },
            "util.gpu": {
                "min": 0,
                "max": 0,
                "mean": 0.0,
                "std": 0.0
            },
            "util.memory": {
                "min": 0,
                "max": 0,
                "mean": 0.0,
                "std": 0.0
            },
            "power_usage": {
                "min": 0.959,
                "max": 2.356,
                "mean": 1.3965478192421914,
                "std": 0.15089206519916412
            },
            "memory.used": {
                "min": 16384000,
                "max": 16384000,
                "mean": 16384000.0,
                "std": 0.0
            },
            "memory.free": {
                "min": 16892231680,
                "max": 16892231680,
                "mean": 16892231680.0,
                "std": 0.0
            },
            "total_power_draw": 3915.329995209719
        },
        "total": {
            "start_unix": 1677705750.389476,
            "end_unix": 1677708554.02096,
            "nr_measurements": 55898,
            "total_power_draw": 3915.329995209719,
            "start_utc": "2023-03-01 21:22:30",
            "end_utc": "2023-03-01 22:09:14",
            "total_duration": 2803.6314840316772
        }
    },
    "execution_platform": {
        "System": "Linux",
        "Node Name": "ls8ws022",
        "Release": "5.4.0-137-generic",
        "Version": "#154-Ubuntu SMP Thu Jan 5 17:03:22 UTC 2023",
        "Machine": "x86_64",
        "Processor": "Intel(R) Xeon(R) W-2155 CPU @ 3.30GHz",
        "Physical cores": 10,
        "Total cores": 20,
        "Max Frequency": 4500.0,
        "Min Frequency": 1200.0,
        "Current Frequency": 1215.1726999999998,
        "Total": 67103240192,
        "Available": 64367718400,
        "Used": 1992843264
    },
    "config": {
        "dataset": "temperature_rain_dataset_without_missing_values",
        "model": "wavenet",
        "output_dir": "mnt_data/results",
        "epochs": 100,
        "datadir": "mnt_data/data",
        "cpu_monitor_interval": 0.05,
        "gpu_monitor_interval": 0.05,
        "seed": 42,
        "timestamp": "2023_03_01_21_22_30",
        "lag": 9,
        "external_forecast_horizon": 30,
        "train_logdir": "mnt_data/results/train_2023_03_01_21_17_39"
    },
    "full_log": "mnt_data/results_merged/infer_2023_03_01_21_22_30.tar.gz"
}