{
    "directory_name": "train_2023_03_19_12_19_29",
    "results": {
        "history": {
            "loss": [
                52598327.32061538,
                4712621.011692308,
                2004184.5193846154,
                1184420.1403076923,
                762473.5175384615,
                509696.3378461538,
                364551.52246153844,
                291899.5190769231,
                242404.9246153846,
                216793.62753846153,
                184780.14538461537,
                169995.14153846152,
                154417.1243076923,
                140503.09276923077,
                126183.10707692307,
                115935.52261538462,
                112884.08953846154,
                101755.20384615385,
                92582.02576923076,
                89151.16838461539,
                83096.05476923077,
                76661.6793076923,
                70396.37284615384
            ]
        },
        "start": 1679224771.2237396,
        "end": 1679224815.9545686,
        "model": null
    },
    "requirements": [
        "# 3.7.7 (default, Mar 23 2020, 22:36:06)",
        "# [GCC 7.3.0]",
        "wrapt==1.11.2",
        "typed-ast==1.4.0",
        "six==1.12.0",
        "setuptools==41.6.0",
        "pytz==2019.3",
        "python-dateutil==2.8.0",
        "pyparsing==2.4.2",
        "pylint==2.4.3",
        "numpy==1.17.3",
        "mccabe==0.6.1",
        "matplotlib==3.1.1",
        "lazy-object-proxy==1.4.3",
        "kiwisolver==1.1.0",
        "isort==4.3.21",
        "cycler==0.10.0",
        "astroid==2.3.2",
        "zipp==3.14.0",
        "xgboost==1.6.2",
        "wheel==0.37.1",
        "werkzeug==2.2.3",
        "urllib3==1.26.14",
        "typing-extensions==4.4.0",
        "tqdm==4.64.1",
        "toolz==0.12.0",
        "threadpoolctl==3.1.0",
        "tenacity==8.2.2",
        "scipy==1.7.3",
        "scikit-learn==1.0.2",
        "rpy2==2.9.4",
        "requests==2.28.2",
        "reportlab==3.6.12",
        "qrcode==7.4.2",
        "pypng==0.20220715.0",
        "pynvml==11.4.1",
        "pymupdf==1.21.1",
        "pydantic==1.10.4",
        "pyarrow==8.0.0",
        "py-rapl==0.1",
        "py-cpuinfo==9.0.0",
        "psutil==5.9.4",
        "plotly==5.13.1",
        "pip==22.3.1",
        "pint==0.18",
        "pillow==9.4.0",
        "pandas==1.3.5",
        "packaging==23.0",
        "orjson==3.8.5",
        "mxnet==1.9.1",
        "markupsafe==2.1.1",
        "joblib==1.2.0",
        "jinja2==3.1.2",
        "itsdangerous==2.1.2",
        "importlib-metadata==6.0.0",
        "idna==3.4",
        "graphviz==0.8.4",
        "gluonts==0.11.8",
        "fuzzywuzzy==0.18.0",
        "flask==2.2.3",
        "dash==2.8.1",
        "dash-table==5.0.0",
        "dash-html-components==2.0.0",
        "dash-core-components==2.0.0",
        "dash-bootstrap-components==1.4.0",
        "codecarbon==2.1.4",
        "click==8.1.3",
        "charset-normalizer==3.0.1",
        "certifi==2022.12.7",
        "arrow==1.2.3"
    ],
    "config": {
        "dataset": "m4_weekly_dataset",
        "model": "deepfactor",
        "output_dir": "mnt_data/results",
        "ds_seed": 129,
        "epochs": 100,
        "datadir": "mnt_data/data",
        "cpu_monitor_interval": 0.5,
        "seed": 42,
        "timestamp": "2023_03_19_12_19_29"
    },
    "execution_platform": {
        "System": "Linux",
        "Node Name": "ls8ws022",
        "Release": "5.4.0-137-generic",
        "Version": "#154-Ubuntu SMP Thu Jan 5 17:03:22 UTC 2023",
        "Machine": "x86_64",
        "Processor": "Intel(R) Xeon(R) W-2155 CPU @ 3.30GHz",
        "Physical cores": 10,
        "Total cores": 20,
        "Max Frequency": 4500.0,
        "Min Frequency": 1200.0,
        "Current Frequency": 1202.846,
        "Total": 67103240192,
        "Available": 64866111488,
        "Used": 1495404544
    },
    "emissions": {
        "timestamp": {
            "0": "2023-03-19T12:20:15"
        },
        "project_name": {
            "0": "codecarbon"
        },
        "run_id": {
            "0": "e09157a0-31b0-46ce-b670-f0e13da6ac2c"
        },
        "duration": {
            "0": 44.7372727394104
        },
        "emissions": {
            "0": 0.0003138401464067
        },
        "emissions_rate": {
            "0": 0.007015182803719
        },
        "cpu_power": {
            "0": 17.362523028495016
        },
        "gpu_power": {
            "0": 1.305
        },
        "ram_power": {
            "0": 23.43553590774536
        },
        "cpu_energy": {
            "0": 0.0007609071859474
        },
        "gpu_energy": {
            "0": 1.461789068380992e-05
        },
        "ram_energy": {
            "0": 0.000267133217079
        },
        "energy_consumed": {
            "0": 0.0010426582937102
        },
        "country_name": {
            "0": "Germany"
        },
        "country_iso_code": {
            "0": "DEU"
        },
        "region": {
            "0": NaN
        },
        "cloud_provider": {
            "0": NaN
        },
        "cloud_region": {
            "0": NaN
        },
        "os": {
            "0": "Linux-5.4.0-137-generic-x86_64-with-debian-bullseye-sid"
        },
        "python_version": {
            "0": "3.7.7"
        },
        "cpu_count": {
            "0": 20
        },
        "cpu_model": {
            "0": "Intel(R) Xeon(R) W-2155 CPU @ 3.30GHz"
        },
        "gpu_count": {
            "0": 1
        },
        "gpu_model": {
            "0": "1 x Quadro RTX 5000"
        },
        "longitude": {
            "0": NaN
        },
        "latitude": {
            "0": NaN
        },
        "ram_total_size": {
            "0": 62.4947624206543
        },
        "tracking_mode": {
            "0": "machine"
        },
        "on_cloud": {
            "0": "N"
        }
    },
    "full_log": "results/merged/train_2023_03_19_12_19_29.tar.gz"
}