{
    "directory_name": "train_2023_03_20_21_05_05",
    "execution_platform": {
        "System": "Linux",
        "Node Name": "ls8ws022",
        "Release": "5.4.0-137-generic",
        "Version": "#154-Ubuntu SMP Thu Jan 5 17:03:22 UTC 2023",
        "Machine": "x86_64",
        "Processor": "Intel(R) Xeon(R) W-2155 CPU @ 3.30GHz",
        "Physical cores": 10,
        "Total cores": 20,
        "Max Frequency": 4500.0,
        "Min Frequency": 1200.0,
        "Current Frequency": 1205.17935,
        "Total": 67103240192,
        "Available": 64864133120,
        "Used": 1497473024
    },
    "results": {
        "history": {
            "loss": [
                24.321150690714518,
                13.614497426350912,
                12.405602493286132,
                11.365052401224773,
                10.852317250569662,
                10.55415148417155,
                10.400269571940104,
                10.173910217285156,
                10.063443285624187,
                9.893720436096192,
                9.785371119181315,
                9.622032826741536,
                9.52367249806722,
                9.394093780517577,
                9.322289225260416,
                9.207213478088379,
                9.157200915018718,
                9.062990163167317,
                9.035648536682128,
                8.942134539286295,
                8.911490631103515,
                8.848857828776042,
                8.814731826782227,
                8.74710506439209,
                8.716042467753093,
                8.667829221089681,
                8.63705842336019,
                8.589801508585612,
                8.562168401082356,
                8.524485931396484,
                8.492200355529786,
                8.45055726369222
            ]
        },
        "start": 1679342708.5076509,
        "end": 1679343322.979935,
        "model": null
    },
    "requirements": [
        "# 3.7.7 (default, Mar 23 2020, 22:36:06)",
        "# [GCC 7.3.0]",
        "wrapt==1.11.2",
        "typed-ast==1.4.0",
        "six==1.12.0",
        "setuptools==41.6.0",
        "pytz==2019.3",
        "python-dateutil==2.8.0",
        "pyparsing==2.4.2",
        "pylint==2.4.3",
        "numpy==1.17.3",
        "mccabe==0.6.1",
        "matplotlib==3.1.1",
        "lazy-object-proxy==1.4.3",
        "kiwisolver==1.1.0",
        "isort==4.3.21",
        "cycler==0.10.0",
        "astroid==2.3.2",
        "zipp==3.14.0",
        "xgboost==1.6.2",
        "wheel==0.37.1",
        "werkzeug==2.2.3",
        "urllib3==1.26.14",
        "typing-extensions==4.4.0",
        "tqdm==4.64.1",
        "toolz==0.12.0",
        "threadpoolctl==3.1.0",
        "tenacity==8.2.2",
        "scipy==1.7.3",
        "scikit-learn==1.0.2",
        "rpy2==2.9.4",
        "requests==2.28.2",
        "reportlab==3.6.12",
        "qrcode==7.4.2",
        "pypng==0.20220715.0",
        "pynvml==11.4.1",
        "pymupdf==1.21.1",
        "pydantic==1.10.4",
        "pyarrow==8.0.0",
        "py-rapl==0.1",
        "py-cpuinfo==9.0.0",
        "psutil==5.9.4",
        "plotly==5.13.1",
        "pip==22.3.1",
        "pint==0.18",
        "pillow==9.4.0",
        "pandas==1.3.5",
        "packaging==23.0",
        "orjson==3.8.5",
        "mxnet==1.9.1",
        "markupsafe==2.1.1",
        "joblib==1.2.0",
        "jinja2==3.1.2",
        "itsdangerous==2.1.2",
        "importlib-metadata==6.0.0",
        "idna==3.4",
        "graphviz==0.8.4",
        "gluonts==0.11.8",
        "fuzzywuzzy==0.18.0",
        "flask==2.2.3",
        "dash==2.8.1",
        "dash-table==5.0.0",
        "dash-html-components==2.0.0",
        "dash-core-components==2.0.0",
        "dash-bootstrap-components==1.4.0",
        "codecarbon==2.1.4",
        "click==8.1.3",
        "charset-normalizer==3.0.1",
        "certifi==2022.12.7",
        "arrow==1.2.3"
    ],
    "config": {
        "dataset": "pedestrian_counts_dataset",
        "model": "mqcnn",
        "output_dir": "mnt_data/results",
        "ds_seed": 468,
        "epochs": 100,
        "datadir": "mnt_data/data",
        "cpu_monitor_interval": 0.5,
        "seed": 42,
        "timestamp": "2023_03_20_21_05_05"
    },
    "emissions": {
        "timestamp": {
            "0": "2023-03-20T21:15:22"
        },
        "project_name": {
            "0": "codecarbon"
        },
        "run_id": {
            "0": "2366d4f0-bbc5-441e-9a62-53cf8bed1964"
        },
        "duration": {
            "0": 614.4790830612183
        },
        "emissions": {
            "0": 0.0038395864758509
        },
        "emissions_rate": {
            "0": 0.0062485226620292
        },
        "cpu_power": {
            "0": 18.208206665108985
        },
        "gpu_power": {
            "0": 1.4860000000000002
        },
        "ram_power": {
            "0": 23.43553590774536
        },
        "cpu_energy": {
            "0": 0.0088153846381354
        },
        "gpu_energy": {
            "0": 0.0002048322025556
        },
        "ram_energy": {
            "0": 0.0037358844079833
        },
        "energy_consumed": {
            "0": 0.0127561012486743
        },
        "country_name": {
            "0": "Germany"
        },
        "country_iso_code": {
            "0": "DEU"
        },
        "region": {
            "0": NaN
        },
        "cloud_provider": {
            "0": NaN
        },
        "cloud_region": {
            "0": NaN
        },
        "os": {
            "0": "Linux-5.4.0-137-generic-x86_64-with-debian-bullseye-sid"
        },
        "python_version": {
            "0": "3.7.7"
        },
        "cpu_count": {
            "0": 20
        },
        "cpu_model": {
            "0": "Intel(R) Xeon(R) W-2155 CPU @ 3.30GHz"
        },
        "gpu_count": {
            "0": 1
        },
        "gpu_model": {
            "0": "1 x Quadro RTX 5000"
        },
        "longitude": {
            "0": NaN
        },
        "latitude": {
            "0": NaN
        },
        "ram_total_size": {
            "0": 62.4947624206543
        },
        "tracking_mode": {
            "0": "machine"
        },
        "on_cloud": {
            "0": "N"
        }
    },
    "full_log": "results/merged/train_2023_03_20_21_05_05.tar.gz"
}