{
    "directory_name": "train_2023_03_11_10_08_00",
    "execution_platform": {
        "System": "Linux",
        "Node Name": "ls8ws022",
        "Release": "5.4.0-137-generic",
        "Version": "#154-Ubuntu SMP Thu Jan 5 17:03:22 UTC 2023",
        "Machine": "x86_64",
        "Processor": "Intel(R) Xeon(R) W-2155 CPU @ 3.30GHz",
        "Physical cores": 10,
        "Total cores": 20,
        "Max Frequency": 4500.0,
        "Min Frequency": 1200.0,
        "Current Frequency": 1202.9468499999998,
        "Total": 67103240192,
        "Available": 64880533504,
        "Used": 1480499200
    },
    "config": {
        "dataset": "m4_weekly_dataset",
        "model": "gpforecaster",
        "output_dir": "mnt_data/results",
        "epochs": 100,
        "datadir": "mnt_data/data",
        "cpu_monitor_interval": 0.5,
        "seed": 42,
        "timestamp": "2023_03_11_10_08_00"
    },
    "requirements": [
        "# 3.7.7 (default, Mar 23 2020, 22:36:06)",
        "# [GCC 7.3.0]",
        "wrapt==1.11.2",
        "typed-ast==1.4.0",
        "six==1.12.0",
        "setuptools==41.6.0",
        "pytz==2019.3",
        "python-dateutil==2.8.0",
        "pyparsing==2.4.2",
        "pylint==2.4.3",
        "numpy==1.17.3",
        "mccabe==0.6.1",
        "matplotlib==3.1.1",
        "lazy-object-proxy==1.4.3",
        "kiwisolver==1.1.0",
        "isort==4.3.21",
        "cycler==0.10.0",
        "astroid==2.3.2",
        "zipp==3.14.0",
        "xgboost==1.6.2",
        "wheel==0.37.1",
        "werkzeug==2.2.3",
        "urllib3==1.26.14",
        "typing-extensions==4.4.0",
        "tqdm==4.64.1",
        "toolz==0.12.0",
        "threadpoolctl==3.1.0",
        "tenacity==8.2.2",
        "scipy==1.7.3",
        "scikit-learn==1.0.2",
        "rpy2==2.9.4",
        "requests==2.28.2",
        "reportlab==3.6.12",
        "qrcode==7.4.2",
        "pypng==0.20220715.0",
        "pynvml==11.4.1",
        "pymupdf==1.21.1",
        "pydantic==1.10.4",
        "pyarrow==8.0.0",
        "py-rapl==0.1",
        "py-cpuinfo==9.0.0",
        "psutil==5.9.4",
        "plotly==5.13.1",
        "pip==22.3.1",
        "pint==0.18",
        "pillow==9.4.0",
        "pandas==1.3.5",
        "packaging==23.0",
        "orjson==3.8.5",
        "mxnet==1.9.1",
        "markupsafe==2.1.1",
        "joblib==1.2.0",
        "jinja2==3.1.2",
        "itsdangerous==2.1.2",
        "importlib-metadata==6.0.0",
        "idna==3.4",
        "graphviz==0.8.4",
        "gluonts==0.11.8",
        "fuzzywuzzy==0.18.0",
        "flask==2.2.3",
        "dash==2.8.1",
        "dash-table==5.0.0",
        "dash-html-components==2.0.0",
        "dash-core-components==2.0.0",
        "dash-bootstrap-components==1.4.0",
        "codecarbon==2.1.4",
        "click==8.1.3",
        "charset-normalizer==3.0.1",
        "certifi==2022.12.7",
        "arrow==1.2.3"
    ],
    "emissions": {
        "timestamp": {
            "0": "2023-03-11T10:11:32"
        },
        "project_name": {
            "0": "codecarbon"
        },
        "run_id": {
            "0": "c3fdf4ee-5644-48d0-bba5-6e776120ec49"
        },
        "duration": {
            "0": 210.8150134086609
        },
        "emissions": {
            "0": 0.0014109460742606
        },
        "emissions_rate": {
            "0": 0.0066928159026585
        },
        "cpu_power": {
            "0": 17.767052177181775
        },
        "gpu_power": {
            "0": 0.947
        },
        "ram_power": {
            "0": 23.43553590774536
        },
        "cpu_energy": {
            "0": 0.0033559341028006
        },
        "gpu_energy": {
            "0": 5.582096674568118e-05
        },
        "ram_energy": {
            "0": 0.0012757734163694
        },
        "energy_consumed": {
            "0": 0.0046875284859158
        },
        "country_name": {
            "0": "Germany"
        },
        "country_iso_code": {
            "0": "DEU"
        },
        "region": {
            "0": NaN
        },
        "cloud_provider": {
            "0": NaN
        },
        "cloud_region": {
            "0": NaN
        },
        "os": {
            "0": "Linux-5.4.0-137-generic-x86_64-with-debian-bullseye-sid"
        },
        "python_version": {
            "0": "3.7.7"
        },
        "cpu_count": {
            "0": 20
        },
        "cpu_model": {
            "0": "Intel(R) Xeon(R) W-2155 CPU @ 3.30GHz"
        },
        "gpu_count": {
            "0": 1
        },
        "gpu_model": {
            "0": "1 x Quadro RTX 5000"
        },
        "longitude": {
            "0": NaN
        },
        "latitude": {
            "0": NaN
        },
        "ram_total_size": {
            "0": 62.4947624206543
        },
        "tracking_mode": {
            "0": "machine"
        },
        "on_cloud": {
            "0": "N"
        }
    },
    "results": {
        "history": {
            "loss": [
                13760.004595370632,
                10848.367123133035,
                9021.218863311587,
                7364.559250425492,
                5861.865778299717,
                5072.631652234135,
                3806.9768520627326,
                3563.389346135392,
                2808.478789568084,
                2528.923493266728,
                2056.390380410508,
                1857.4546514794752,
                1582.1107967524183,
                1434.167800395686,
                1289.9088439779218,
                1173.6340989201617,
                1101.4286867066662,
                978.8988203471449,
                983.8248661891677,
                905.000395022065,
                888.3481542496846,
                832.7661855779982,
                821.7029754449394,
                778.9101910321307,
                766.6837108905003,
                741.8636661353287,
                724.5294596713649,
                711.1797745552166,
                691.9660012719402,
                676.519369461717,
                667.0400710835867,
                667.2292967228839,
                646.7316721319578,
                646.9877258860676,
                631.642889657949,
                630.015202697501,
                618.6144037110336,
                614.7088989092929,
                608.0511323278548,
                601.3585537954525,
                599.7304272017032,
                584.0991710051431,
                590.8740879632237,
                582.2357604239209,
                581.5445019907704,
                575.3955448266884,
                574.1606280689047,
                568.3944262295278,
                567.0703296978241,
                562.3689780295686,
                560.8060482620942,
                557.7242523562761,
                549.9830102308377,
                553.57674583143,
                550.0099062704577,
                548.4475200913824,
                545.6499975184718,
                544.7421417955516,
                541.4057967407953,
                540.6704373488415,
                537.5790800884748
            ]
        },
        "start": 1678525682.0030925,
        "end": 1678525892.811213,
        "model": null
    },
    "full_log": "results/merged/train_2023_03_11_10_08_00.tar.gz"
}